stouch/__init__.py
stouch/base.py
stouch/cli.py
stouch-0.1.0.post1.dist-info/LICENSE
stouch-0.1.0.post1.dist-info/METADATA
stouch-0.1.0.post1.dist-info/WHEEL
stouch-0.1.0.post1.dist-info/entry_points.txt
stouch-0.1.0.post1.dist-info/RECORD
