Metadata-Version: 2.1
Name: stouch
Version: 0.1.0.post1
Summary: An extensible touch command with plugin support, allowing for enhanced file creation capabilities.
Home-page: https://github.com/azataiot/stouch
License: MIT
Author: Azat
Author-email: 8280770+azataiot@users.noreply.github.com
Requires-Python: >=3.11,<4.0
Classifier: License :: OSI Approved :: MIT License
Classifier: Programming Language :: Python :: 3
Classifier: Programming Language :: Python :: 3.11
Provides-Extra: slugify
Requires-Dist: python-slugify (>=8.0.1,<9.0.0) ; extra == "slugify"
Requires-Dist: typer (>=0.9.0,<0.10.0)
